README.rst
setup.py
djangorestframework_extras.egg-info/PKG-INFO
djangorestframework_extras.egg-info/SOURCES.txt
djangorestframework_extras.egg-info/dependency_links.txt
djangorestframework_extras.egg-info/not-zip-safe
djangorestframework_extras.egg-info/requires.txt
djangorestframework_extras.egg-info/top_level.txt
rest_framework_extras/__init__.py
rest_framework_extras/models.py
rest_framework_extras/serializers.py
rest_framework_extras/tests/__init__.py
rest_framework_extras/tests/forms.py
rest_framework_extras/tests/models.py
rest_framework_extras/tests/test_discover.py
rest_framework_extras/tests/test_users.py
rest_framework_extras/tests/test_views.py
rest_framework_extras/tests/urls.py
rest_framework_extras/tests/settings/110.py
rest_framework_extras/tests/settings/111.py
rest_framework_extras/tests/settings/20.py
rest_framework_extras/tests/settings/__init__.py
rest_framework_extras/users/__init__.py
rest_framework_extras/users/permissions.py
rest_framework_extras/users/serializers.py
rest_framework_extras/users/viewsets.py