Metadata-Version: 1.1
Name: djangorestframework-extras
Version: 0.3.0
Summary: Autogenerate API's for models. Expose core Django functionality. Validate against existing forms.
Home-page: http://github.com/praekelt/djangorestframework-extras
Author: Praekelt Consulting
Author-email: dev@praekelt.com
License: BSD
Platform: UNKNOWN
Classifier: Programming Language :: Python
Classifier: License :: OSI Approved :: BSD License
Classifier: Operating System :: OS Independent
Classifier: Framework :: Django
Classifier: Intended Audience :: Developers
Classifier: Topic :: Internet :: WWW/HTTP :: Dynamic Content
